MANIFEST.in
README.rst
setup.py
bin/duedge
duedge_cli/.sysconfig
duedge_cli/__init__.py
duedge_cli/__main__.py
duedge_cli/utils.py
duedge_cli.egg-info/PKG-INFO
duedge_cli.egg-info/SOURCES.txt
duedge_cli.egg-info/dependency_links.txt
duedge_cli.egg-info/entry_points.txt
duedge_cli.egg-info/requires.txt
duedge_cli.egg-info/top_level.txt
duedge_cli/doc/__init__.py
duedge_cli/doc/overview.txt
duedge_cli/doc/code-example/index.js
duedge_cli/doc/code-example/index.lua
duedge_cli/doc/code-example/index.py
duedge_cli/doc/function/create-function-alias.simple.txt
duedge_cli/doc/function/create-function.simple.txt
duedge_cli/doc/function/create-function.table.txt
duedge_cli/doc/function/delete-function-alias.simple.txt
duedge_cli/doc/function/delete-function.simple.txt
duedge_cli/doc/function/delete-function.table.txt
duedge_cli/doc/function/get-function-alias.simple.txt
duedge_cli/doc/function/get-function-configuration.simple.txt
duedge_cli/doc/function/get-function-configuration.table.txt
duedge_cli/doc/function/get-function.simple.txt
duedge_cli/doc/function/get-function.table.txt
duedge_cli/doc/function/invoke.simple.txt
duedge_cli/doc/function/invoke.table.txt
duedge_cli/doc/function/list-debug-logs.simple.txt
duedge_cli/doc/function/list-function-aliases.simple.txt
duedge_cli/doc/function/list-functions.simple.txt
duedge_cli/doc/function/list-functions.table.txt
duedge_cli/doc/function/publish-version.simple.txt
duedge_cli/doc/function/publish-version.table.txt
duedge_cli/doc/function/update-function-alias.simple.txt
duedge_cli/doc/function/update-function-code.simple.txt
duedge_cli/doc/function/update-function-code.table.txt
duedge_cli/doc/function/update-function-configuration.simple.txt
duedge_cli/doc/function/update-function-configuration.table.txt
duedge_cli/doc/system/configure.simple.txt
duedge_cli/doc/system/init-function.simple.txt
duedge_cli/doc/system/update.simple.txt
duedge_cli/doc/trigger/create-rate-limit.simple.txt
duedge_cli/doc/trigger/create-trigger.simple.txt
duedge_cli/doc/trigger/create-trigger.table.txt
duedge_cli/doc/trigger/delete-rate-limit.simple.txt
duedge_cli/doc/trigger/delete-trigger.simple.txt
