Metadata-Version: 1.1
Name: duedge-cli
Version: 1.0.9
Summary: duedge command line tool
Home-page: https://duedge.baidu.com
Author: xuyanfei, likewei
Author-email: likewei@baidu.com
License: MIT
Platform: UNKNOWN
Classifier: Programming Language :: Python :: 2.7
Classifier: Programming Language :: Python :: 3.7
